tracescopio/__init__.py
tracescopio/scopio.py
tracescopio/decorators/__init__.py
tracescopio/decorators/traceme.py
tracescopio/middleware/__init__.py
tracescopio/middleware/telemetria.py
tracescopio-2.0.1.dist-info/LICENSE
tracescopio-2.0.1.dist-info/METADATA
tracescopio-2.0.1.dist-info/WHEEL
tracescopio-2.0.1.dist-info/top_level.txt
tracescopio-2.0.1.dist-info/RECORD
