Metadata-Version: 2.1
Name: tracescopio
Version: 2.0.1
Summary: Tracescopio - um capturador simples de tracebacks
Home-page: UNKNOWN
Author: Tercio A Oliveira
Author-email: t3rcio@gmail.com
License: UNKNOWN
Keywords: python,traceback
Platform: UNKNOWN
Classifier: Development Status :: 4 - Beta
Classifier: Intended Audience :: Developers
Classifier: Programming Language :: Python :: 3
Classifier: License :: OSI Approved :: GNU General Public License (GPL)
Requires-Dist: django
Requires-Dist: requests
